calculator_gskv_m1_s1/__init__.py
calculator_gskv_m1_s1/main.py
calculator_gskv_m1_s1-0.1.4.dist-info/LICENSE
calculator_gskv_m1_s1-0.1.4.dist-info/WHEEL
calculator_gskv_m1_s1-0.1.4.dist-info/METADATA
calculator_gskv_m1_s1-0.1.4.dist-info/RECORD
