Metadata-Version: 2.1
Name: calculator_gskv_m1_s1
Version: 0.1.4
Summary: This module contains a Calculator
Author-email: Gediminas Skvarnavicius <gediminas.skvarnavicius@gmail.com>
Classifier: License :: OSI Approved :: MIT License
Project-URL: Home, https://github.com/gediminas-skvarnavicius/calculator_gskv_m1_s1
